ivi_sdk/__init__.py
ivi_sdk/ivi_client.py
ivi_sdk/api/item/definition_pb2.py
ivi_sdk/api/item/definition_pb2_grpc.py
ivi_sdk/api/item/rpc_pb2.py
ivi_sdk/api/item/rpc_pb2_grpc.py
ivi_sdk/api/itemtype/definition_pb2.py
ivi_sdk/api/itemtype/definition_pb2_grpc.py
ivi_sdk/api/itemtype/rpc_pb2.py
ivi_sdk/api/itemtype/rpc_pb2_grpc.py
ivi_sdk/api/order/definition_pb2.py
ivi_sdk/api/order/definition_pb2_grpc.py
ivi_sdk/api/order/payment_pb2.py
ivi_sdk/api/order/payment_pb2_grpc.py
ivi_sdk/api/order/rpc_pb2.py
ivi_sdk/api/order/rpc_pb2_grpc.py
ivi_sdk/api/payment/definition_pb2.py
ivi_sdk/api/payment/definition_pb2_grpc.py
ivi_sdk/api/payment/rpc_pb2.py
ivi_sdk/api/payment/rpc_pb2_grpc.py
ivi_sdk/api/player/definition_pb2.py
ivi_sdk/api/player/definition_pb2_grpc.py
ivi_sdk/api/player/rpc_pb2.py
ivi_sdk/api/player/rpc_pb2_grpc.py
ivi_sdk/common/common_pb2.py
ivi_sdk/common/common_pb2_grpc.py
ivi_sdk/common/finalization_pb2.py
ivi_sdk/common/finalization_pb2_grpc.py
ivi_sdk/common/sort_pb2.py
ivi_sdk/common/sort_pb2_grpc.py
ivi_sdk/common/item/definition_pb2.py
ivi_sdk/common/item/definition_pb2_grpc.py
ivi_sdk/common/itemtype/definition_pb2.py
ivi_sdk/common/itemtype/definition_pb2_grpc.py
ivi_sdk/common/order/definition_pb2.py
ivi_sdk/common/order/definition_pb2_grpc.py
ivi_sdk/common/player/definition_pb2.py
ivi_sdk/common/player/definition_pb2_grpc.py
ivi_sdk/streams/common_pb2.py
ivi_sdk/streams/common_pb2_grpc.py
ivi_sdk/streams/item/stream_pb2.py
ivi_sdk/streams/item/stream_pb2_grpc.py
ivi_sdk/streams/itemtype/stream_pb2.py
ivi_sdk/streams/itemtype/stream_pb2_grpc.py
ivi_sdk/streams/order/stream_pb2.py
ivi_sdk/streams/order/stream_pb2_grpc.py
ivi_sdk/streams/ping/stream_pb2.py
ivi_sdk/streams/ping/stream_pb2_grpc.py
ivi_sdk/streams/player/stream_pb2.py
ivi_sdk/streams/player/stream_pb2_grpc.py
ivi_sdk-0.1.dist-info/METADATA
ivi_sdk-0.1.dist-info/WHEEL
ivi_sdk-0.1.dist-info/top_level.txt
ivi_sdk-0.1.dist-info/RECORD
