Metadata-Version: 2.1
Name: ivi-sdk
Version: 0.1
Summary: Simple IVI gRPC stream API wrapper
Home-page: UNKNOWN
License: UNKNOWN
Platform: UNKNOWN
Requires-Python: >=3.6
Requires-Dist: grpcio (==1.34.0)
Requires-Dist: protobuf (<4.0dev,>=3.5.0.post1)
